customtitlebar/__init__.py
customtitlebar/data.py
customtitlebar/titlebar.py
customtitlebar/asset/tk.ico
customtitlebar/asset/dark/close_100.png
customtitlebar/asset/dark/close_50.png
customtitlebar/asset/dark/fullwin_100.png
customtitlebar/asset/dark/fullwin_50.png
customtitlebar/asset/dark/minisize_100.png
customtitlebar/asset/dark/minisize_50.png
customtitlebar/asset/dark/togglefull_100.png
customtitlebar/asset/dark/togglefull_50.png
customtitlebar/asset/light/close_100.png
customtitlebar/asset/light/close_50.png
customtitlebar/asset/light/fullwin_100.png
customtitlebar/asset/light/fullwin_50.png
customtitlebar/asset/light/minisize_100.png
customtitlebar/asset/light/minisize_50.png
customtitlebar/asset/light/togglefull_100.png
customtitlebar/asset/light/togglefull_50.png
CustomTkinterTitlebar-1.0.8.6.dist-info/LICENSE
CustomTkinterTitlebar-1.0.8.6.dist-info/METADATA
CustomTkinterTitlebar-1.0.8.6.dist-info/WHEEL
CustomTkinterTitlebar-1.0.8.6.dist-info/top_level.txt
CustomTkinterTitlebar-1.0.8.6.dist-info/RECORD
