Metadata-Version: 2.1
Name: CustomTkinterTitlebar
Version: 1.0.8.6
Summary: This is a 📚project can help you to have a custom titlebar! 这是一个可以创建自定义标题栏的📚项目
Home-page: https://github.com/littlewhitecloud/CustomTkinterTitlebar
Author: littlewhitecloud
Author-email: q1141926647@163.com
License: MIT
Classifier: Development Status :: 5 - Production/Stable
Classifier: Intended Audience :: Developers
Classifier: License :: OSI Approved :: MIT License
Classifier: Programming Language :: Python :: 3.10
Classifier: Programming Language :: Python :: 3.11
Classifier: Programming Language :: Python :: 3.12
License-File: LICENSE
